openadapt_evals/__init__.py
openadapt_evals/adapters/__init__.py
openadapt_evals/adapters/base.py
openadapt_evals/adapters/waa/__init__.py
openadapt_evals/adapters/waa/live.py
openadapt_evals/adapters/waa/mock.py
openadapt_evals/agents/__init__.py
openadapt_evals/agents/api_agent.py
openadapt_evals/agents/base.py
openadapt_evals/agents/baseline_agent.py
openadapt_evals/agents/policy_agent.py
openadapt_evals/agents/retrieval_agent.py
openadapt_evals/agents/scripted_agent.py
openadapt_evals/benchmarks/__init__.py
openadapt_evals/benchmarks/azure.py
openadapt_evals/benchmarks/cli.py
openadapt_evals/benchmarks/config.py
openadapt_evals/benchmarks/data_collection.py
openadapt_evals/benchmarks/health_checker.py
openadapt_evals/benchmarks/live_tracker.py
openadapt_evals/benchmarks/monitoring.py
openadapt_evals/benchmarks/runner.py
openadapt_evals/benchmarks/viewer.py
openadapt_evals/cli/__init__.py
openadapt_evals/cli/main.py
openadapt_evals/cli/vm.py
openadapt_evals/evaluation/__init__.py
openadapt_evals/evaluation/client.py
openadapt_evals/evaluation/discovery.py
openadapt_evals/infrastructure/__init__.py
openadapt_evals/infrastructure/azure_ops_tracker.py
openadapt_evals/infrastructure/ssh_tunnel.py
openadapt_evals/infrastructure/vm_monitor.py
openadapt_evals/integrations/__init__.py
openadapt_evals/integrations/demo_wandb.py
openadapt_evals/integrations/fixtures.py
openadapt_evals/integrations/wandb_logger.py
openadapt_evals/integrations/wandb_reports.py
openadapt_evals/metrics/__init__.py
openadapt_evals/server/__init__.py
openadapt_evals/server/evaluate_endpoint.py
openadapt_evals/server/waa_server_patch.py
openadapt_evals/shared_ui/__init__.py
openadapt_evals/shared_ui/keyboard_shortcuts.py
openadapt_evals/waa_deploy/Dockerfile
openadapt_evals/waa_deploy/__init__.py
openadapt_evals/waa_deploy/api_agent.py
openadapt_evals/waa_deploy/start_waa_server.bat
openadapt_evals-0.1.2.dist-info/METADATA
openadapt_evals-0.1.2.dist-info/WHEEL
openadapt_evals-0.1.2.dist-info/entry_points.txt
openadapt_evals-0.1.2.dist-info/licenses/LICENSE
openadapt_evals-0.1.2.dist-info/RECORD
