Metadata-Version: 2.4
Name: openadapt-evals
Version: 0.1.2
Summary: Evaluation infrastructure for GUI agent benchmarks
Project-URL: Homepage, https://github.com/OpenAdaptAI/openadapt-evals
Project-URL: Repository, https://github.com/OpenAdaptAI/openadapt-evals
Project-URL: Documentation, https://github.com/OpenAdaptAI/openadapt-evals#readme
Project-URL: Bug Tracker, https://github.com/OpenAdaptAI/openadapt-evals/issues
Author-email: Richard Abrich <richard@openadapt.ai>
Maintainer-email: OpenAdaptAI <contact@openadapt.ai>
License-Expression: MIT
License-File: LICENSE
Keywords: agent,ai,automation,benchmark,evaluation,gui
Classifier: Development Status :: 3 - Alpha
Classifier: Intended Audience :: Developers
Classifier: Intended Audience :: Science/Research
Classifier: License :: OSI Approved :: MIT License
Classifier: Operating System :: OS Independent
Classifier: Programming Language :: Python :: 3
Classifier: Programming Language :: Python :: 3.10
Classifier: Programming Language :: Python :: 3.11
Classifier: Programming Language :: Python :: 3.12
Classifier: Topic :: Scientific/Engineering :: Artificial Intelligence
Classifier: Topic :: Software Development :: Testing
Requires-Python: >=3.10
Requires-Dist: httpx>=0.25.0
Requires-Dist: open-clip-torch>=2.20.0
Requires-Dist: pillow>=10.0.0
Requires-Dist: python-dotenv>=1.2.1
Requires-Dist: requests>=2.28.0
Requires-Dist: tenacity>=8.2.0
Provides-Extra: all
Requires-Dist: azure-ai-ml>=1.12.0; extra == 'all'
Requires-Dist: azure-identity>=1.15.0; extra == 'all'
Requires-Dist: flask-cors>=4.0.0; extra == 'all'
Requires-Dist: flask>=3.0.0; extra == 'all'
Requires-Dist: openadapt-retrieval>=0.1.0; extra == 'all'
Requires-Dist: pytest>=8.0.0; extra == 'all'
Requires-Dist: requests>=2.28.0; extra == 'all'
Requires-Dist: ruff>=0.1.0; extra == 'all'
Requires-Dist: wandb>=0.16.0; extra == 'all'
Provides-Extra: azure
Requires-Dist: azure-ai-ml>=1.12.0; extra == 'azure'
Requires-Dist: azure-identity>=1.15.0; extra == 'azure'
Provides-Extra: dev
Requires-Dist: pytest>=8.0.0; extra == 'dev'
Requires-Dist: ruff>=0.1.0; extra == 'dev'
Provides-Extra: retrieval
Requires-Dist: openadapt-retrieval>=0.1.0; extra == 'retrieval'
Provides-Extra: test
Requires-Dist: anthropic>=0.76.0; extra == 'test'
Provides-Extra: viewer
Requires-Dist: flask-cors>=4.0.0; extra == 'viewer'
Requires-Dist: flask>=3.0.0; extra == 'viewer'
Provides-Extra: waa
Requires-Dist: requests>=2.28.0; extra == 'waa'
Provides-Extra: wandb
Requires-Dist: wandb>=0.16.0; extra == 'wandb'
